string_utils_pip/__init__.py
string_utils_pip/clean.py
string_utils_pip/frequency.py
string_utils_pip/palindrome.py
string_utils_pip/removeduplicates.py
string_utils_pip/vowels.py
string_utils_pip-0.0.1.dist-info/METADATA
string_utils_pip-0.0.1.dist-info/WHEEL
string_utils_pip-0.0.1.dist-info/licenses/LICENSE
string_utils_pip-0.0.1.dist-info/RECORD
